gncn_test/test1.py
gncn_test/test2.py
gncn_test-0.0.0.3.dist-info/METADATA
gncn_test-0.0.0.3.dist-info/WHEEL
gncn_test-0.0.0.3.dist-info/top_level.txt
gncn_test-0.0.0.3.dist-info/RECORD
