Metadata-Version: 2.1
Name: gncn-test
Version: 0.0.0.3
Summary: My First Test Package
Home-page: https://blog.naver.com/vouov273
Author: Sumin SON
Author-email: a01027815586@gmail.com
License: MIT
Platform: UNKNOWN
Requires-Python: >=3
